{
    "053bdf5c-7c76-bf31-9d2c-cbae97313559": {
        "paletteKey": "FlexLayoutCol",
        "designerReference": [
            {
                "_key": "style",
                "_value": "",
                "_type": "kv",
                "_attrDef": "p"
            },
            {
                "_key": "class",
                "_value": "",
                "_type": "kv",
                "_attrDef": "p"
            },
            {
                "_key": "fxFlex",
                "_value": "",
                "_type": "kv",
                "_attrDef": "p"
            },
            {
                "_key": "fxLayoutGap",
                "_value": "",
                "_type": "kv",
                "_attrDef": "p"
            },
            {
                "_key": "wrap",
                "_value": "wrap",
                "_type": "a",
                "_attrDef": "p"
            },
            {
                "_key": "layoutAlign",
                "_value": "start",
                "_type": "a",
                "_attrDef": "p"
            },
            {
                "_key": "pLayoutAlign",
                "_value": "stretch",
                "_type": "a",
                "_attrDef": "p"
            },
            {
                "_key": "fxShow",
                "_value": "true",
                "_type": "kv",
                "_attrDef": "p"
            },
            {
                "_key": "fxHide",
                "_value": "false",
                "_type": "kv",
                "_attrDef": "p"
            }
        ],
        "470b2a4c-2a3c-1d31-8361-2edf96a3153d": {
            "paletteKey": "NG-Form",
            "designerReference": [
                {
                    "_key": "style",
                    "_value": "",
                    "_type": "kv",
                    "_attrDef": "p"
                },
                {
                    "_key": "class",
                    "_value": "",
                    "_type": "kv",
                    "_attrDef": "p"
                }
            ],
            "29b34837-5ec9-e743-082c-509ed11df504": {
                "paletteKey": "NG-Stepper",
                "designerReference": [
                    {
                        "_key": "style",
                        "_value": "",
                        "_type": "kv",
                        "_attrDef": "p"
                    },
                    {
                        "_key": "class",
                        "_value": "",
                        "_type": "kv",
                        "_attrDef": "p"
                    },
                    {
                        "_key": "[linear]",
                        "_value": "",
                        "_type": "kv",
                        "_attrDef": "p"
                    },
                    {
                        "_key": "type",
                        "_value": "vertical",
                        "_type": "a",
                        "_attrDef": "p"
                    },
                    {
                        "_key": "matHorizontalStepper",
                        "_value": "",
                        "_type": "vk",
                        "_attrDef": "p"
                    },
                    {
                        "_key": "matVerticalStepper",
                        "_value": "",
                        "_type": "vk",
                        "_attrDef": "p"
                    },
                    {
                        "_key": "[selected]",
                        "_value": "",
                        "_type": "kv",
                        "_attrDef": "p"
                    },
                    {
                        "_key": "[selectedIndex]",
                        "_value": "",
                        "_type": "kv",
                        "_attrDef": "p"
                    },
                    {
                        "_key": "(selectionChange)",
                        "_value": "",
                        "_type": "kv",
                        "_attrDef": "p"
                    }
                ],
                "4784dde6-776d-5ecf-141d-38724bd5b709": {
                    "paletteKey": "NG-Step",
                    "designerReference": [
                        {
                            "_key": "style",
                            "_value": "",
                            "_type": "kv",
                            "_attrDef": "p"
                        },
                        {
                            "_key": "class",
                            "_value": "",
                            "_type": "kv",
                            "_attrDef": "p"
                        },
                        {
                            "_key": "label",
                            "_value": "The basics",
                            "_type": "kv",
                            "_attrDef": "p"
                        },
                        {
                            "_key": "completed",
                            "_value": "",
                            "_type": "kv",
                            "_attrDef": "p"
                        },
                        {
                            "_key": "editable",
                            "_value": "",
                            "_type": "kv",
                            "_attrDef": "p"
                        },
                        {
                            "_key": "interacted",
                            "_value": "",
                            "_type": "kv",
                            "_attrDef": "p"
                        },
                        {
                            "_key": "optional",
                            "_value": "",
                            "_type": "kv",
                            "_attrDef": "p"
                        },
                        {
                            "_key": "[stepControl]",
                            "_value": "",
                            "_type": "kv",
                            "_attrDef": "p"
                        }
                    ],
                    "45c2e812-08e2-46c7-b27d-6942b5468d79": {
                        "paletteKey": "FlexLayoutCol",
                        "designerReference": [
                            {
                                "_key": "style",
                                "_value": "",
                                "_type": "kv",
                                "_attrDef": "p"
                            },
                            {
                                "_key": "class",
                                "_value": "",
                                "_type": "kv",
                                "_attrDef": "p"
                            },
                            {
                                "_key": "fxFlex",
                                "_value": "",
                                "_type": "kv",
                                "_attrDef": "p"
                            },
                            {
                                "_key": "fxLayoutGap",
                                "_value": "",
                                "_type": "kv",
                                "_attrDef": "p"
                            },
                            {
                                "_key": "wrap",
                                "_value": "wrap",
                                "_type": "a",
                                "_attrDef": "p"
                            },
                            {
                                "_key": "layoutAlign",
                                "_value": "start",
                                "_type": "a",
                                "_attrDef": "p"
                            },
                            {
                                "_key": "pLayoutAlign",
                                "_value": "stretch",
                                "_type": "a",
                                "_attrDef": "p"
                            },
                            {
                                "_key": "fxShow",
                                "_value": "true",
                                "_type": "kv",
                                "_attrDef": "p"
                            },
                            {
                                "_key": "fxHide",
                                "_value": "false",
                                "_type": "kv",
                                "_attrDef": "p"
                            }
                        ],
                        "d1098537-f649-159d-8be2-c990b166564a": {
                            "paletteKey": "NG-Select",
                            "designerReference": [
                                {
                                    "_key": "style",
                                    "_value": "",
                                    "_type": "kv",
                                    "_attrDef": "p"
                                },
                                {
                                    "_key": "class",
                                    "_value": "",
                                    "_type": "kv",
                                    "_attrDef": "p"
                                },
                                {
                                    "_key": "placeholder",
                                    "_value": "Select mentee",
                                    "_type": "kv",
                                    "_attrDef": "p"
                                },
                                {
                                    "_key": "[(ngModel)]",
                                    "_value": "",
                                    "_type": "kv",
                                    "_attrDef": "p"
                                },
                                {
                                    "_key": "required",
                                    "_value": "required",
                                    "_type": "a",
                                    "_attrDef": "p"
                                },
                                {
                                    "_key": "multiple",
                                    "_value": "",
                                    "_type": "a",
                                    "_attrDef": "p"
                                },
                                {
                                    "_key": "(openedChange)",
                                    "_value": "",
                                    "_type": "kv",
                                    "_attrDef": "p"
                                },
                                {
                                    "_key": "(selectionChange)",
                                    "_value": "",
                                    "_type": "kv",
                                    "_attrDef": "p"
                                },
                                {
                                    "_key": "*ngFor",
                                    "_value": "let name of mentee",
                                    "_type": "kv",
                                    "_attrDef": "p"
                                },
                                {
                                    "_key": "[value]",
                                    "_value": "name.name",
                                    "_type": "kv",
                                    "_attrDef": "p"
                                },
                                {
                                    "_key": "optiondata",
                                    "_value": "{{ name.name }}",
                                    "_type": "a",
                                    "_attrDef": "p"
                                }
                            ]
                        },
                        "a3bc6176-a7cf-42d4-12d7-1cbb77743261": {
                            "paletteKey": "NG-DatePicker",
                            "designerReference": [
                                {
                                    "_key": "style",
                                    "_value": "",
                                    "_type": "kv",
                                    "_attrDef": "p"
                                },
                                {
                                    "_key": "class",
                                    "_value": "",
                                    "_type": "kv",
                                    "_attrDef": "p"
                                },
                                {
                                    "_key": "placeholder",
                                    "_value": "Date",
                                    "_type": "kv",
                                    "_attrDef": "p"
                                },
                                {
                                    "_key": "value",
                                    "_value": "",
                                    "_type": "kv",
                                    "_attrDef": "p"
                                },
                                {
                                    "_key": "[min]",
                                    "_value": "",
                                    "_type": "kv",
                                    "_attrDef": "p"
                                },
                                {
                                    "_key": "[max]",
                                    "_value": "",
                                    "_type": "kv",
                                    "_attrDef": "p"
                                },
                                {
                                    "_key": "[startAt]",
                                    "_value": "",
                                    "_type": "kv",
                                    "_attrDef": "p"
                                },
                                {
                                    "_key": "startView",
                                    "_value": "",
                                    "_type": "kv",
                                    "_attrDef": "p"
                                },
                                {
                                    "_key": "touchUi",
                                    "_value": "",
                                    "_type": "kv",
                                    "_attrDef": "p"
                                },
                                {
                                    "_key": "id",
                                    "_value": "",
                                    "_type": "kv",
                                    "_attrDef": "p"
                                },
                                {
                                    "_key": "(dateChange)",
                                    "_value": "",
                                    "_type": "kv",
                                    "_attrDef": "p"
                                },
                                {
                                    "_key": "(dateInput)",
                                    "_value": "",
                                    "_type": "kv",
                                    "_attrDef": "p"
                                },
                                {
                                    "_key": "opened",
                                    "_value": "",
                                    "_type": "kv",
                                    "_attrDef": "p"
                                },
                                {
                                    "_key": "disabled",
                                    "_value": "",
                                    "_type": "kv",
                                    "_attrDef": "p"
                                },
                                {
                                    "_key": "(open)",
                                    "_value": "",
                                    "_type": "kv",
                                    "_attrDef": "p"
                                },
                                {
                                    "_key": "(close)",
                                    "_value": "",
                                    "_type": "kv",
                                    "_attrDef": "p"
                                },
                                {
                                    "_key": "[matDatepickerFilter]",
                                    "_value": "",
                                    "_type": "kv",
                                    "_attrDef": "p"
                                },
                                {
                                    "_key": "[(ngModel)]",
                                    "_value": "today.today",
                                    "_type": "kv",
                                    "_attrDef": "p"
                                },
                                {
                                    "_key": "name",
                                    "_value": "today",
                                    "_type": "kv",
                                    "_attrDef": "p"
                                },
                                {
                                    "_key": "picker",
                                    "_value": "picker",
                                    "_type": "ma",
                                    "_attrDef": "p"
                                }
                            ]
                        },
                        "43bca9c6-753c-50d1-55d1-b9332d5fdd70": {
                            "paletteKey": "NG-Input",
                            "designerReference": [
                                {
                                    "_key": "style",
                                    "_value": "",
                                    "_type": "kv",
                                    "_attrDef": "p"
                                },
                                {
                                    "_key": "class",
                                    "_value": "",
                                    "_type": "kv",
                                    "_attrDef": "p"
                                },
                                {
                                    "_key": "placeholder",
                                    "_value": "Location",
                                    "_type": "kv",
                                    "_attrDef": "p"
                                },
                                {
                                    "_key": "value",
                                    "_value": "",
                                    "_type": "kv",
                                    "_attrDef": "p"
                                },
                                {
                                    "_key": "required",
                                    "_value": "required",
                                    "_type": "a",
                                    "_attrDef": "p"
                                },
                                {
                                    "_key": "[(ngModel)]",
                                    "_value": "",
                                    "_type": "kv",
                                    "_attrDef": "p"
                                },
                                {
                                    "_key": "color",
                                    "_value": "",
                                    "_type": "kv",
                                    "_attrDef": "p"
                                },
                                {
                                    "_key": "name",
                                    "_value": "",
                                    "_type": "kv",
                                    "_attrDef": "p"
                                },
                                {
                                    "_key": "type",
                                    "_value": "",
                                    "_type": "kv",
                                    "_attrDef": "p"
                                }
                            ]
                        }
                    }
                },
                "77fc4df5-bd0e-53d2-ee43-48cd965a807e": {
                    "paletteKey": "NG-Step",
                    "designerReference": [
                        {
                            "_key": "style",
                            "_value": "",
                            "_type": "kv",
                            "_attrDef": "p"
                        },
                        {
                            "_key": "class",
                            "_value": "",
                            "_type": "kv",
                            "_attrDef": "p"
                        },
                        {
                            "_key": "label",
                            "_value": "Goals",
                            "_type": "kv",
                            "_attrDef": "p"
                        },
                        {
                            "_key": "completed",
                            "_value": "",
                            "_type": "kv",
                            "_attrDef": "p"
                        },
                        {
                            "_key": "editable",
                            "_value": "",
                            "_type": "kv",
                            "_attrDef": "p"
                        },
                        {
                            "_key": "interacted",
                            "_value": "",
                            "_type": "kv",
                            "_attrDef": "p"
                        },
                        {
                            "_key": "optional",
                            "_value": "",
                            "_type": "kv",
                            "_attrDef": "p"
                        },
                        {
                            "_key": "[stepControl]",
                            "_value": "",
                            "_type": "kv",
                            "_attrDef": "p"
                        }
                    ],
                    "55817837-80b7-5465-fa14-1de1f2f1df21": {
                        "paletteKey": "FlexLayoutCol",
                        "designerReference": [
                            {
                                "_key": "style",
                                "_value": "",
                                "_type": "kv",
                                "_attrDef": "p"
                            },
                            {
                                "_key": "class",
                                "_value": "",
                                "_type": "kv",
                                "_attrDef": "p"
                            },
                            {
                                "_key": "fxFlex",
                                "_value": "",
                                "_type": "kv",
                                "_attrDef": "p"
                            },
                            {
                                "_key": "fxLayoutGap",
                                "_value": "",
                                "_type": "kv",
                                "_attrDef": "p"
                            },
                            {
                                "_key": "wrap",
                                "_value": "wrap",
                                "_type": "a",
                                "_attrDef": "p"
                            },
                            {
                                "_key": "layoutAlign",
                                "_value": "start",
                                "_type": "a",
                                "_attrDef": "p"
                            },
                            {
                                "_key": "pLayoutAlign",
                                "_value": "stretch",
                                "_type": "a",
                                "_attrDef": "p"
                            },
                            {
                                "_key": "fxShow",
                                "_value": "true",
                                "_type": "kv",
                                "_attrDef": "p"
                            },
                            {
                                "_key": "fxHide",
                                "_value": "false",
                                "_type": "kv",
                                "_attrDef": "p"
                            }
                        ],
                        "1805964b-ac63-64f8-1f5d-d695d3569284": {
                            "paletteKey": "FlexLayoutCol",
                            "designerReference": [
                                {
                                    "_key": "style",
                                    "_value": "",
                                    "_type": "kv",
                                    "_attrDef": "p"
                                },
                                {
                                    "_key": "class",
                                    "_value": "",
                                    "_type": "kv",
                                    "_attrDef": "p"
                                },
                                {
                                    "_key": "fxFlex",
                                    "_value": "",
                                    "_type": "kv",
                                    "_attrDef": "p"
                                },
                                {
                                    "_key": "fxLayoutGap",
                                    "_value": "",
                                    "_type": "kv",
                                    "_attrDef": "p"
                                },
                                {
                                    "_key": "wrap",
                                    "_value": "wrap",
                                    "_type": "a",
                                    "_attrDef": "p"
                                },
                                {
                                    "_key": "layoutAlign",
                                    "_value": "start",
                                    "_type": "a",
                                    "_attrDef": "p"
                                },
                                {
                                    "_key": "pLayoutAlign",
                                    "_value": "stretch",
                                    "_type": "a",
                                    "_attrDef": "p"
                                },
                                {
                                    "_key": "fxShow",
                                    "_value": "true",
                                    "_type": "kv",
                                    "_attrDef": "p"
                                },
                                {
                                    "_key": "fxHide",
                                    "_value": "false",
                                    "_type": "kv",
                                    "_attrDef": "p"
                                }
                            ],
                            "8fb557a7-61d9-1604-70b4-95d5c269f94f": {
                                "paletteKey": "NG-slide",
                                "designerReference": [
                                    {
                                        "_key": "style",
                                        "_value": "",
                                        "_type": "kv",
                                        "_attrDef": "p"
                                    },
                                    {
                                        "_key": "class",
                                        "_value": "",
                                        "_type": "kv",
                                        "_attrDef": "p"
                                    },
                                    {
                                        "_key": "required",
                                        "_value": "",
                                        "_type": "kv",
                                        "_attrDef": "p"
                                    },
                                    {
                                        "_key": "text",
                                        "_value": "Was the Goal met?",
                                        "_type": "a",
                                        "_attrDef": "p"
                                    },
                                    {
                                        "_key": "labelPosition",
                                        "_value": "before",
                                        "_type": "kv",
                                        "_attrDef": "p"
                                    },
                                    {
                                        "_key": "name",
                                        "_value": "",
                                        "_type": "kv",
                                        "_attrDef": "p"
                                    },
                                    {
                                        "_key": "id",
                                        "_value": "",
                                        "_type": "kv",
                                        "_attrDef": "p"
                                    },
                                    {
                                        "_key": "(change)",
                                        "_value": "",
                                        "_type": "kv",
                                        "_attrDef": "p"
                                    },
                                    {
                                        "_key": "checked",
                                        "_value": "",
                                        "_type": "kv",
                                        "_attrDef": "p"
                                    },
                                    {
                                        "_key": "color",
                                        "_value": "",
                                        "_type": "kv",
                                        "_attrDef": "p"
                                    }
                                ]
                            },
                            "9bdd06b0-6ae8-6927-67dd-ebaad39c76e9": {
                                "paletteKey": "NG-Input",
                                "designerReference": [
                                    {
                                        "_key": "style",
                                        "_value": "",
                                        "_type": "kv",
                                        "_attrDef": "p"
                                    },
                                    {
                                        "_key": "class",
                                        "_value": "",
                                        "_type": "kv",
                                        "_attrDef": "p"
                                    },
                                    {
                                        "_key": "placeholder",
                                        "_value": "why not?",
                                        "_type": "kv",
                                        "_attrDef": "p"
                                    },
                                    {
                                        "_key": "value",
                                        "_value": "",
                                        "_type": "kv",
                                        "_attrDef": "p"
                                    },
                                    {
                                        "_key": "required",
                                        "_value": "required",
                                        "_type": "a",
                                        "_attrDef": "p"
                                    },
                                    {
                                        "_key": "[(ngModel)]",
                                        "_value": "",
                                        "_type": "kv",
                                        "_attrDef": "p"
                                    },
                                    {
                                        "_key": "color",
                                        "_value": "",
                                        "_type": "kv",
                                        "_attrDef": "p"
                                    },
                                    {
                                        "_key": "name",
                                        "_value": "",
                                        "_type": "kv",
                                        "_attrDef": "p"
                                    },
                                    {
                                        "_key": "type",
                                        "_value": "",
                                        "_type": "kv",
                                        "_attrDef": "p"
                                    }
                                ]
                            },
                            "c23ffa03-1df8-a3ef-7c74-f0615760193e": {
                                "paletteKey": "NG-slide",
                                "designerReference": [
                                    {
                                        "_key": "style",
                                        "_value": "",
                                        "_type": "kv",
                                        "_attrDef": "p"
                                    },
                                    {
                                        "_key": "class",
                                        "_value": "",
                                        "_type": "kv",
                                        "_attrDef": "p"
                                    },
                                    {
                                        "_key": "required",
                                        "_value": "",
                                        "_type": "kv",
                                        "_attrDef": "p"
                                    },
                                    {
                                        "_key": "text",
                                        "_value": "New Goal",
                                        "_type": "a",
                                        "_attrDef": "p"
                                    },
                                    {
                                        "_key": "labelPosition",
                                        "_value": "before",
                                        "_type": "kv",
                                        "_attrDef": "p"
                                    },
                                    {
                                        "_key": "name",
                                        "_value": "",
                                        "_type": "kv",
                                        "_attrDef": "p"
                                    },
                                    {
                                        "_key": "id",
                                        "_value": "",
                                        "_type": "kv",
                                        "_attrDef": "p"
                                    },
                                    {
                                        "_key": "(change)",
                                        "_value": "",
                                        "_type": "kv",
                                        "_attrDef": "p"
                                    },
                                    {
                                        "_key": "checked",
                                        "_value": "",
                                        "_type": "kv",
                                        "_attrDef": "p"
                                    },
                                    {
                                        "_key": "color",
                                        "_value": "",
                                        "_type": "kv",
                                        "_attrDef": "p"
                                    }
                                ]
                            }
                        },
                        "9388d798-6ca9-c8fb-ed86-18847af970dc": {
                            "paletteKey": "FlexLayoutCol",
                            "designerReference": [
                                {
                                    "_key": "style",
                                    "_value": "",
                                    "_type": "kv",
                                    "_attrDef": "p"
                                },
                                {
                                    "_key": "class",
                                    "_value": "",
                                    "_type": "kv",
                                    "_attrDef": "p"
                                },
                                {
                                    "_key": "fxFlex",
                                    "_value": "",
                                    "_type": "kv",
                                    "_attrDef": "p"
                                },
                                {
                                    "_key": "fxLayoutGap",
                                    "_value": "",
                                    "_type": "kv",
                                    "_attrDef": "p"
                                },
                                {
                                    "_key": "wrap",
                                    "_value": "wrap",
                                    "_type": "a",
                                    "_attrDef": "p"
                                },
                                {
                                    "_key": "layoutAlign",
                                    "_value": "start",
                                    "_type": "a",
                                    "_attrDef": "p"
                                },
                                {
                                    "_key": "pLayoutAlign",
                                    "_value": "stretch",
                                    "_type": "a",
                                    "_attrDef": "p"
                                },
                                {
                                    "_key": "fxShow",
                                    "_value": "true",
                                    "_type": "kv",
                                    "_attrDef": "p"
                                },
                                {
                                    "_key": "fxHide",
                                    "_value": "false",
                                    "_type": "kv",
                                    "_attrDef": "p"
                                }
                            ],
                            "267d699c-0bfa-db71-9fd2-8675d1699e54": {
                                "paletteKey": "NG-Select",
                                "designerReference": [
                                    {
                                        "_key": "style",
                                        "_value": "",
                                        "_type": "kv",
                                        "_attrDef": "p"
                                    },
                                    {
                                        "_key": "class",
                                        "_value": "",
                                        "_type": "kv",
                                        "_attrDef": "p"
                                    },
                                    {
                                        "_key": "placeholder",
                                        "_value": "Category",
                                        "_type": "kv",
                                        "_attrDef": "p"
                                    },
                                    {
                                        "_key": "[(ngModel)]",
                                        "_value": "",
                                        "_type": "kv",
                                        "_attrDef": "p"
                                    },
                                    {
                                        "_key": "required",
                                        "_value": "required",
                                        "_type": "a",
                                        "_attrDef": "p"
                                    },
                                    {
                                        "_key": "multiple",
                                        "_value": "",
                                        "_type": "a",
                                        "_attrDef": "p"
                                    },
                                    {
                                        "_key": "(openedChange)",
                                        "_value": "",
                                        "_type": "kv",
                                        "_attrDef": "p"
                                    },
                                    {
                                        "_key": "(selectionChange)",
                                        "_value": "",
                                        "_type": "kv",
                                        "_attrDef": "p"
                                    },
                                    {
                                        "_key": "*ngFor",
                                        "_value": "let data of metadata",
                                        "_type": "kv",
                                        "_attrDef": "p"
                                    },
                                    {
                                        "_key": "[value]",
                                        "_value": "data.name",
                                        "_type": "kv",
                                        "_attrDef": "p"
                                    },
                                    {
                                        "_key": "optiondata",
                                        "_value": "{{ data.name }}",
                                        "_type": "a",
                                        "_attrDef": "p"
                                    }
                                ]
                            }
                        }
                    }
                },
                "a77b3388-ad15-7a23-d5df-349428779623": {
                    "paletteKey": "NG-Step",
                    "designerReference": [
                        {
                            "_key": "style",
                            "_value": "",
                            "_type": "kv",
                            "_attrDef": "p"
                        },
                        {
                            "_key": "class",
                            "_value": "",
                            "_type": "kv",
                            "_attrDef": "p"
                        },
                        {
                            "_key": "label",
                            "_value": "Additional comments",
                            "_type": "kv",
                            "_attrDef": "p"
                        },
                        {
                            "_key": "completed",
                            "_value": "",
                            "_type": "kv",
                            "_attrDef": "p"
                        },
                        {
                            "_key": "editable",
                            "_value": "",
                            "_type": "kv",
                            "_attrDef": "p"
                        },
                        {
                            "_key": "interacted",
                            "_value": "",
                            "_type": "kv",
                            "_attrDef": "p"
                        },
                        {
                            "_key": "optional",
                            "_value": "",
                            "_type": "kv",
                            "_attrDef": "p"
                        },
                        {
                            "_key": "[stepControl]",
                            "_value": "",
                            "_type": "kv",
                            "_attrDef": "p"
                        }
                    ],
                    "2f219d65-8406-7334-f405-f1afdf64de90": {
                        "paletteKey": "FlexLayoutCol",
                        "designerReference": [
                            {
                                "_key": "style",
                                "_value": "",
                                "_type": "kv",
                                "_attrDef": "p"
                            },
                            {
                                "_key": "class",
                                "_value": "",
                                "_type": "kv",
                                "_attrDef": "p"
                            },
                            {
                                "_key": "fxFlex",
                                "_value": "",
                                "_type": "kv",
                                "_attrDef": "p"
                            },
                            {
                                "_key": "fxLayoutGap",
                                "_value": "",
                                "_type": "kv",
                                "_attrDef": "p"
                            },
                            {
                                "_key": "wrap",
                                "_value": "wrap",
                                "_type": "a",
                                "_attrDef": "p"
                            },
                            {
                                "_key": "layoutAlign",
                                "_value": "start",
                                "_type": "a",
                                "_attrDef": "p"
                            },
                            {
                                "_key": "pLayoutAlign",
                                "_value": "stretch",
                                "_type": "a",
                                "_attrDef": "p"
                            },
                            {
                                "_key": "fxShow",
                                "_value": "true",
                                "_type": "kv",
                                "_attrDef": "p"
                            },
                            {
                                "_key": "fxHide",
                                "_value": "false",
                                "_type": "kv",
                                "_attrDef": "p"
                            }
                        ],
                        "82ebea24-2dc4-9a78-2fbf-98c1f0192f86": {
                            "paletteKey": "NG-Input",
                            "designerReference": [
                                {
                                    "_key": "style",
                                    "_value": "",
                                    "_type": "kv",
                                    "_attrDef": "p"
                                },
                                {
                                    "_key": "class",
                                    "_value": "",
                                    "_type": "kv",
                                    "_attrDef": "p"
                                },
                                {
                                    "_key": "placeholder",
                                    "_value": "Additional Info",
                                    "_type": "kv",
                                    "_attrDef": "p"
                                },
                                {
                                    "_key": "value",
                                    "_value": "",
                                    "_type": "kv",
                                    "_attrDef": "p"
                                },
                                {
                                    "_key": "required",
                                    "_value": "required",
                                    "_type": "a",
                                    "_attrDef": "p"
                                },
                                {
                                    "_key": "[(ngModel)]",
                                    "_value": "",
                                    "_type": "kv",
                                    "_attrDef": "p"
                                },
                                {
                                    "_key": "color",
                                    "_value": "",
                                    "_type": "kv",
                                    "_attrDef": "p"
                                },
                                {
                                    "_key": "name",
                                    "_value": "",
                                    "_type": "kv",
                                    "_attrDef": "p"
                                },
                                {
                                    "_key": "type",
                                    "_value": "",
                                    "_type": "kv",
                                    "_attrDef": "p"
                                }
                            ]
                        }
                    }
                }
            }
        }
    }
}
